<?xml version="1.0" encoding="UTF-8"?>
<site>
   <feature url="features/org.eclipse.ecf.provider.jms_feature_0.0.0.jmsqualifier.jar" id="org.eclipse.ecf.provider.jms_feature" version="0.0.0.jmsqualifier">
      <category name="Eclipse Communication Framework (ECF) Extras"/>
   </feature>
   <feature url="features/org.eclipse.ecf.provider.skype_feature_0.0.0.skypequalifier.jar" id="org.eclipse.ecf.provider.skype_feature" version="0.0.0.skypequalifier">
      <category name="Eclipse Communication Framework (ECF) Extras"/>
   </feature>
   <feature url="features/org.eclipse.ecf.provider.yahoo_feature_0.0.0.yahooqualifier.jar" id="org.eclipse.ecf.provider.yahoo_feature" version="0.0.0.yahooqualifier">
      <category name="Eclipse Communication Framework (ECF) Extras"/>
   </feature>
   <feature url="features/org.eclipse.ecf.provider.jgroups_feature_0.0.0.jgroupsqualifier.jar" id="org.eclipse.ecf.provider.jgroups_feature" version="0.0.0.jgroupsqualifier">
      <category name="Eclipse Communication Framework (ECF) Extras"/>
   </feature>
   <category-def name="Eclipse Communication Framework (ECF) Extras" label="Eclipse Communication Framework (ECF) Extras">
      <description>
         ECF Extras are features not available via the Eclipse Foundation (Yahoo provider, Skype provider, JMS provider).
      </description>
   </category-def>
</site>
